MANIFEST.in
README.rst
setup.py
bin/dataspectra
dataspectra/__init__.py
dataspectra/dataset_class.py
dataspectra/datastore_funcs.py
dataspectra/dsvisualizer.py
dataspectra/dsvisualizer_convert_input.py
dataspectra/figure_class.py
dataspectra/helper_funcs.py
dataspectra/panel_class.py
dataspectra/search_lookup.py
dataspectra/sidebar_class.py
dataspectra/site_class.py
dataspectra/site_generator.py
dataspectra/tutorial_prep_brainspan.py
dataspectra.egg-info/PKG-INFO
dataspectra.egg-info/SOURCES.txt
dataspectra.egg-info/dependency_links.txt
dataspectra.egg-info/not-zip-safe
dataspectra.egg-info/requires.txt
dataspectra.egg-info/top_level.txt
dataspectra/aefiles/.DS_Store
dataspectra/aefiles/app.yaml
dataspectra/aefiles/lib/__init__.py
dataspectra/aefiles/lib/__init__.pyc
dataspectra/aefiles/lib/cloudstorage/__init__.py
dataspectra/aefiles/lib/cloudstorage/__init__.pyc
dataspectra/aefiles/lib/cloudstorage/api_utils.py
dataspectra/aefiles/lib/cloudstorage/api_utils.pyc
dataspectra/aefiles/lib/cloudstorage/cloudstorage_api.py
dataspectra/aefiles/lib/cloudstorage/cloudstorage_api.pyc
dataspectra/aefiles/lib/cloudstorage/common.py
dataspectra/aefiles/lib/cloudstorage/common.pyc
dataspectra/aefiles/lib/cloudstorage/errors.py
dataspectra/aefiles/lib/cloudstorage/errors.pyc
dataspectra/aefiles/lib/cloudstorage/rest_api.py
dataspectra/aefiles/lib/cloudstorage/rest_api.pyc
dataspectra/aefiles/lib/cloudstorage/storage_api.py
dataspectra/aefiles/lib/cloudstorage/storage_api.pyc
dataspectra/aefiles/lib/cloudstorage/test_utils.py
dataspectra/aefiles/lib/cloudstorage/test_utils.pyc
dataspectra/aefiles/old_items/tmp/search_lookup_file.txt
dataspectra/aefiles/scripts/__init__.py
dataspectra/aefiles/scripts/__init__.pyc
dataspectra/aefiles/scripts/load_funcs.py
dataspectra/aefiles/scripts/load_funcs.pyc
dataspectra/aefiles/scripts/load_parameters.py
dataspectra/aefiles/scripts/load_parameters.pyc
dataspectra/aefiles/scripts/main_page.py
dataspectra/aefiles/scripts/main_page.pyc
dataspectra/aefiles/scripts/mapreduce.py
dataspectra/aefiles/scripts/password.py
dataspectra/aefiles/scripts/password.pyc
dataspectra/aefiles/scripts/query_data.py
dataspectra/aefiles/scripts/query_data.pyc
