Metadata-Version: 1.0
Name: dataspectra
Version: 0.3.5
Summary: Creates interactive web visualizations
Home-page: https://dataspectra.org
Author: Ryosuke Kita
Author-email: ryo@dataspectra.org
License: MIT
Platform: UNKNOWN
